csstar/VERSION
csstar/__init__.py
csstar/__main__.py
csstar/evaluate_alignment.py
csstar/file_content.py
csstar/file_convert.py
csstar/parse_arguments.py
csstar/utilities_file.py
csstar/utilities_system.py
csstar/data/ResGANNOT_srst2.fasta.gz
csstar-2.1.0.dist-info/WHEEL
csstar-2.1.0.dist-info/METADATA
csstar-2.1.0.dist-info/RECORD
