Metadata-Version: 2.1
Name: csstar
Version: 2.1.0
Summary: fetches version name from file, otherwise reports non-numeric string
Home-page: https://github.com/chrisgulvik/c-SSTAR
Author: Christopher A. Gulvik
Author-email: submit-github-issue@missing.net
Classifier: Development Status :: 5 - Production/Stable
Classifier: Environment :: Console
Classifier: Intended Audience :: Science/Research
Classifier: License :: OSI Approved :: Apache Software License
Classifier: Natural Language :: English
Classifier: Programming Language :: Python :: 2.7
Classifier: Topic :: Scientific/Engineering :: Bio-Informatics
Requires-Dist: biopython>=1.68
Requires-Dist: setuptools
Requires-Dist: flake8 ; extra == "tests"
Requires-Dist: pytest ; extra == "tests"
Requires-Dist: pytest-cov ; extra == "tests"
Project-URL: Bug Tracker, https://github.com/chrisgulvik/c-SSTAR/issues
Project-URL: Continuous Integration, https://github.com/chrisgulvik/c-SSTAR/actions
Project-URL: Documentation, https://github.com/chrisgulvik/c-SSTAR/blob/master/README.md
Project-URL: Release Versions, https://github.com/chrisgulvik/c-SSTAR/releases
Provides-Extra: tests
